wagtail_content_admin/__init__.py
wagtail_content_admin/apps.py
wagtail_content_admin/blocks.py
wagtail_content_admin/browser.py
wagtail_content_admin/chooser.py
wagtail_content_admin/config.py
wagtail_content_admin/content_admin.py
wagtail_content_admin/default_settings.py
wagtail_content_admin/delegate.py
wagtail_content_admin/form_fields.py
wagtail_content_admin/frontend.py
wagtail_content_admin/widgets.py
wagtail_content_admin/static/wagtail_content_admin/css/wagtail_content_admin.css
wagtail_content_admin/static/wagtail_content_admin/js/wagtail_content_admin.js
wagtail_content_admin/templates/wagtail_content_admin/browser_index.html
wagtail_content_admin/templates/wagtail_content_admin/browser_results.html
wagtail_content_admin/templates/wagtail_content_admin/content_chooser.html
wagtail_content_admin/templates/wagtail_content_admin/content_chooser_results.html
wagtail_content_admin/templates/wagtail_content_admin/blocks/content_render_block.html
wagtail_content_admin/templates/wagtail_content_admin/blocks/content_render_block_base.html
wagtail_content_admin/templates/wagtail_content_admin/widgets/compare.html
wagtail_content_admin/templates/wagtail_content_admin/widgets/content_chooser.html
wagtail_content_admin/templatetags/__init__.py
wagtail_content_admin/templatetags/wagtail_content_admin_tags.py
wagtail_content_admin-4.1.1.dist-info/AUTHORS.txt
wagtail_content_admin-4.1.1.dist-info/LICENSE.txt
wagtail_content_admin-4.1.1.dist-info/METADATA
wagtail_content_admin-4.1.1.dist-info/WHEEL
wagtail_content_admin-4.1.1.dist-info/top_level.txt
wagtail_content_admin-4.1.1.dist-info/RECORD
